[
  {
    "id": "1",
    "name": "Vercel Dashboard",
    "description": "Deployment and hosting management",
    "url": "https://vercel.com/dashboard",
    "order": 1
  },
  {
    "id": "2",
    "name": "GitHub Repository",
    "description": "Source code and version control",
    "url": "https://github.com/adam-3owl/veya-internal-tooling",
    "order": 2
  },
  {
    "id": "3",
    "name": "Analytics Dashboard",
    "description": "View analytics and metrics data",
    "url": "https://analytics.veya.co",
    "order": 3
  }
]